LICENSE-BSD.txt
MANIFEST.in
README.rst
setup.py
jexp/__init__.py
jexp/expression.py
jexp/tests.py
jexp.egg-info/PKG-INFO
jexp.egg-info/SOURCES.txt
jexp.egg-info/dependency_links.txt
jexp.egg-info/not-zip-safe
jexp.egg-info/top_level.txt