Metadata-Version: 1.0
Name: jexp
Version: 0.1.2
Summary: A simple Javascript expression builder written for Python.
Home-page: http://packages.python.org/jexp
Author: Matt Luongo
Author-email: mhluongo@gmail.com
License: UNKNOWN
Platform: posix
Classifier: Development Status :: 1 - Planning
Classifier: Intended Audience :: Developers
Classifier: License :: OSI Approved :: BSD License
Classifier: Operating System :: POSIX
Classifier: Programming Language :: Python
